sopel_rainbow/__init__.py
sopel_rainbow/plugin.py
sopel_rainbow-0.2.0.dist-info/COPYING
sopel_rainbow-0.2.0.dist-info/METADATA
sopel_rainbow-0.2.0.dist-info/WHEEL
sopel_rainbow-0.2.0.dist-info/entry_points.txt
sopel_rainbow-0.2.0.dist-info/top_level.txt
sopel_rainbow-0.2.0.dist-info/RECORD
